mdpeditor/__init__.py
mdpeditor/__main__.py
mdpeditor/arguments.py
mdpeditor/compile.py
mdpeditor/explain.py
mdpeditor/runner.py
mdpeditor/tabcompletion.py
mdpeditor/mdpblocks/__init__.py
mdpeditor/mdpblocks/process.py
mdpeditor/mdpblocks/read.py
mdpeditor/mdpblocks/continuation/__init__.py
mdpeditor/mdpblocks/continuation/from-previous-md.mdp
mdpeditor/mdpblocks/default/__init__.py
mdpeditor/mdpblocks/default/parameters.mdp
mdpeditor/mdpblocks/density_guided/__init__.py
mdpeditor/mdpblocks/density_guided/vanilla.mdp
mdpeditor/mdpblocks/density_guided/vanilla.py
mdpeditor/mdpblocks/force_field/__init__.py
mdpeditor/mdpblocks/force_field/amber.mdp
mdpeditor/mdpblocks/force_field/charmm-monolayer.mdp
mdpeditor/mdpblocks/force_field/charmm.mdp
mdpeditor/mdpblocks/output/__init__.py
mdpeditor/mdpblocks/output/minimal.mdp
mdpeditor/mdpblocks/pressure/__init__.py
mdpeditor/mdpblocks/pressure/atmospheric.mdp
mdpeditor/mdpblocks/pressure/membrane.mdp
mdpeditor/mdpblocks/temperature/300K-protein-separate.mdp
mdpeditor/mdpblocks/temperature/__init__.py
mdpeditor/mdpblocks/type/__init__.py
mdpeditor/mdpblocks/type/energy-minimisation.mdp
mdpeditor/mdpblocks/type/molecular-dynamics.mdp
mdpeditor/parameterhelp/__init__.py
mdpeditor/parameterhelp/mdp-options.rst
mdpeditor-1.2.5.dist-info/COPYING
mdpeditor-1.2.5.dist-info/LICENSE
mdpeditor-1.2.5.dist-info/METADATA
mdpeditor-1.2.5.dist-info/WHEEL
mdpeditor-1.2.5.dist-info/entry_points.txt
mdpeditor-1.2.5.dist-info/top_level.txt
mdpeditor-1.2.5.dist-info/RECORD
