Metadata-Version: 2.1
Name: mdpeditor
Version: 1.2.5
Summary: Edit simulation parameter input files for GROMACS
Home-page: https://gitlab.com/cblau/mdpeditor
Author: Christian Blau
Author-email: cblau.mail@gmail.com
License: UNKNOWN
Project-URL: Bug Tracker, https://gitlab.com/cblau/mdpeditor/issues
Keywords: molecular dynamics,GROMACS
Platform: UNKNOWN
Classifier: Programming Language :: Python :: 3
Classifier: Programming Language :: Python :: 3 :: Only
Classifier: Development Status :: 4 - Beta
Classifier: License :: OSI Approved :: GNU General Public License v3 or later (GPLv3+)
Classifier: Operating System :: OS Independent
Requires-Python: >=3.8
License-File: LICENSE
License-File: COPYING
Requires-Dist: argparse
Requires-Dist: configparser
Requires-Dist: rich
